odoo/addons/website_sale_partner_restrict_payment_acquirer/README.rst
odoo/addons/website_sale_partner_restrict_payment_acquirer/__init__.py
odoo/addons/website_sale_partner_restrict_payment_acquirer/__manifest__.py
odoo/addons/website_sale_partner_restrict_payment_acquirer/i18n/ca.po
odoo/addons/website_sale_partner_restrict_payment_acquirer/i18n/es.po
odoo/addons/website_sale_partner_restrict_payment_acquirer/i18n/website_sale_partner_restrict_payment_acquirer.pot
odoo/addons/website_sale_partner_restrict_payment_acquirer/models/__init__.py
odoo/addons/website_sale_partner_restrict_payment_acquirer/models/payment_acquirer.py
odoo/addons/website_sale_partner_restrict_payment_acquirer/readme/CONTRIBUTORS.rst
odoo/addons/website_sale_partner_restrict_payment_acquirer/readme/DESCRIPTION.rst
odoo/addons/website_sale_partner_restrict_payment_acquirer/readme/USAGE.rst
odoo/addons/website_sale_partner_restrict_payment_acquirer/static/description/checkout_acquirers.png
odoo/addons/website_sale_partner_restrict_payment_acquirer/static/description/icon.png
odoo/addons/website_sale_partner_restrict_payment_acquirer/static/description/index.html
odoo/addons/website_sale_partner_restrict_payment_acquirer/static/description/partner_form_allowed_acquirers.png
odoo/addons/website_sale_partner_restrict_payment_acquirer/static/description/public_user.png
odoo/addons/website_sale_partner_restrict_payment_acquirer/tests/__init__.py
odoo/addons/website_sale_partner_restrict_payment_acquirer/tests/test_payment_acquirer.py
odoo_addon_website_sale_partner_restrict_payment_acquirer-15.0.1.0.0.2.dist-info/METADATA
odoo_addon_website_sale_partner_restrict_payment_acquirer-15.0.1.0.0.2.dist-info/WHEEL
odoo_addon_website_sale_partner_restrict_payment_acquirer-15.0.1.0.0.2.dist-info/top_level.txt
odoo_addon_website_sale_partner_restrict_payment_acquirer-15.0.1.0.0.2.dist-info/RECORD
